maml/__init__.py
maml/apps/__init__.py
maml/apps/bowsr/__init__.py
maml/apps/bowsr/acquisition.py
maml/apps/bowsr/optimizer.py
maml/apps/bowsr/perturbation.py
maml/apps/bowsr/preprocessing.py
maml/apps/bowsr/target_space.py
maml/apps/bowsr/model/__init__.py
maml/apps/bowsr/model/base.py
maml/apps/bowsr/model/cgcnn.py
maml/apps/bowsr/model/dft.py
maml/apps/bowsr/model/megnet.py
maml/apps/bowsr/model/tests/test_cgcnn.py
maml/apps/gbe/__init__.py
maml/apps/gbe/describer.py
maml/apps/gbe/presetfeatures.py
maml/apps/gbe/utils.py
maml/apps/pes/__init__.py
maml/apps/pes/_base.py
maml/apps/pes/_gap.py
maml/apps/pes/_lammps.py
maml/apps/pes/_mtp.py
maml/apps/pes/_nnp.py
maml/apps/pes/_snap.py
maml/apps/pes/params/08g.mtp
maml/apps/pes/params/GAP.json
maml/apps/pes/params/MTini.json
maml/apps/pes/params/NNinput.json
maml/apps/pes/templates/defect/in.defect
maml/apps/pes/templates/efs/in.efs
maml/apps/pes/templates/elastic/displace.template
maml/apps/pes/templates/elastic/in.elastic
maml/apps/pes/templates/elastic/init.template
maml/apps/pes/templates/elastic/potential.template
maml/apps/pes/templates/neb/in.neb
maml/apps/pes/templates/neb/in.relax
maml/apps/pes/templates/relax/in.relax
maml/apps/symbolic/__init__.py
maml/apps/symbolic/_feature_generator.py
maml/apps/symbolic/_selectors.py
maml/apps/symbolic/_selectors_cvxpy.py
maml/apps/symbolic/_sis.py
maml/base/__init__.py
maml/base/_data.py
maml/base/_describer.py
maml/base/_feature_batch.py
maml/base/_mixin.py
maml/base/_model.py
maml/data/__init__.py
maml/data/_mp.py
maml/data/_url.py
maml/describers/__init__.py
maml/describers/_composition.py
maml/describers/_m3gnet.py
maml/describers/_matminer.py
maml/describers/_megnet.py
maml/describers/_rdf.py
maml/describers/_site.py
maml/describers/_spectrum.py
maml/describers/_structure.py
maml/describers/data/elemental_embedding_1MEGNet_layer.json
maml/describers/data/elemental_embedding_1MEGNet_layer_length_16.json
maml-2025.4.3.dist-info/licenses/LICENSE
maml-2025.4.3.dist-info/METADATA
maml-2025.4.3.dist-info/WHEEL
maml-2025.4.3.dist-info/top_level.txt
maml-2025.4.3.dist-info/RECORD
