Metadata-Version: 2.4
Name: maml
Version: 2025.4.3
Summary: MAterials Machine Learning (maml) is a machine learning library for materials science.
Author-email: Chi Chen <t1ko@ucsd.edu>, Yunxing Zuo <marcel.nassar@intel.com>, Ji Qi <j1qi@ucsd.edu>, Shyue Ping Ong <ongsp@ucsd.edu>
License: BSD-3-Clause
Keywords: materials,interatomic potential,force field,science,property prediction,AI,machine learning,graph,deep learning
Classifier: Development Status :: 4 - Beta
Classifier: Intended Audience :: Science/Research
Classifier: License :: OSI Approved :: BSD License
Classifier: Operating System :: OS Independent
Classifier: Programming Language :: Python :: 3.10
Classifier: Programming Language :: Python :: 3.11
Classifier: Programming Language :: Python :: 3
Classifier: Topic :: Scientific/Engineering :: Chemistry
Classifier: Topic :: Scientific/Engineering :: Information Analysis
Classifier: Topic :: Scientific/Engineering :: Physics
Classifier: Topic :: Software Development :: Libraries :: Python Modules
Requires-Python: >=3.10
License-File: LICENSE
Requires-Dist: numpy
Requires-Dist: scipy
Requires-Dist: pymatgen
Requires-Dist: mp-api
Requires-Dist: scikit-learn>=1.6.1
Provides-Extra: symbolic
Requires-Dist: cvxpy; extra == "symbolic"
Provides-Extra: deep
Requires-Dist: tensorflow>=2; extra == "deep"
Dynamic: license-file
